flypp/.DS_Store
flypp/__init__.py
flypp/egg.py
flypp/flypp.gif
flypp/main.py
flypp/__pycache__/egg.cpython-310.pyc
flypp-521.dist-info/LICENSE
flypp-521.dist-info/METADATA
flypp-521.dist-info/WHEEL
flypp-521.dist-info/entry_points.txt
flypp-521.dist-info/top_level.txt
flypp-521.dist-info/RECORD
